{
    "missions": [],
    "stages": [
        {
            "stageType": "ACTIVITY",
            "difficulty": "NORMAL",
            "performanceStageFlag": "NORMAL_STAGE",
            "diffGroup": "NONE",
            "unlockCondition": [
                {
                    "stageId": "main_01-10",
                    "completeState": "PASS"
                }
            ],
            "stageId": "act13mini_01",
            "levelId": "Activities/act13mini/level_act13mini_01",
            "zoneId": "act13mini_zone1",
            "code": "BW-1",
            "name": "\u5371\u697c\u6e10\u6e83",
            "description": "\u8981\u62ef\u6551\u4e00\u5ea7\u5c8c\u5c8c\u53ef\u5371\u7684\u5927\u53a6\uff0c\u9996\u5148\u5f97\u770b\u89c1\u90a3\u4e9b\u6816\u8eab\u5728\u7816\u74e6\u4e4b\u4e2d\u7684\u5fae\u5c0f\u8839\u866b\u3002",
            "hardStagedId": "act13mini_01#f#",
            "dangerLevel": "LV.20",
            "dangerPoint": -1.0,
            "loadingPicId": "loading2",
            "canPractice": true,
            "canBattleReplay": true,
            "apCost": 9,
            "apFailReturn": 8,
            "etItemId": null,
            "etCost": -1,
            "etFailReturn": -1,
            "etButtonStyle": null,
            "apProtectTimes": 1,
            "diamondOnceDrop": 1,
            "practiceTicketCost": 1,
            "dailyStageDifficulty": 0,
            "expGain": 90,
            "goldGain": 90,
            "loseExpGain": 0,
            "loseGoldGain": 0,
            "passFavor": 8,
            "completeFavor": 9,
            "slProgress": 0,
            "displayMainItem": null,
            "hilightMark": false,
            "bossMark": false,
            "isPredefined": false,
            "isHardPredefined": false,
            "isSkillSelectablePredefined": false,
            "isStoryOnly": false,
            "appearanceStyle": "MAIN_NORMAL",
            "stageDropInfo": {
                "firstPassRewards": null,
                "firstCompleteRewards": null,
                "passRewards": null,
                "completeRewards": null,
                "displayRewards": [
                    {
                        "type": "ACTIVITY_ITEM",
                        "id": "act13mini_token_can",
                        "dropType": "COMPLETE"
                    },
                    {
                        "type": "ACTIVITY_ITEM",
                        "id": "act13mini_token_can",
                        "dropType": "SPECIAL"
                    },
                    {
                        "type": "MATERIAL",
                        "id": "30031",
                        "dropType": "NORMAL"
                    },
                    {
                        "type": "MATERIAL",
                        "id": "30061",
                        "dropType": "NORMAL"
                    },
                    {
                        "type": "MATERIAL",
                        "id": "30041",
                        "dropType": "NORMAL"
                    },
                    {
                        "type": "MATERIAL",
                        "id": "30051",
                        "dropType": "NORMAL"
                    },
                    {
                        "type": "MATERIAL",
                        "id": "30021",
                        "dropType": "NORMAL"
                    },
                    {
                        "type": "MATERIAL",
                        "id": "30011",
                        "dropType": "NORMAL"
                    },
                    {
                        "type": "DIAMOND",
                        "id": "4002",
                        "dropType": "COMPLETE"
                    }
                ],
                "displayDetailRewards": [
                    {
                        "occPercent": "ALWAYS",
                        "type": "ACTIVITY_ITEM",
                        "id": "act13mini_token_can",
                        "dropType": "COMPLETE"
                    },
                    {
                        "occPercent": "ALWAYS",
                        "type": "ACTIVITY_ITEM",
                        "id": "act13mini_token_can",
                        "dropType": "SPECIAL"
                    },
                    {
                        "occPercent": "OFTEN",
                        "type": "MATERIAL",
                        "id": "30031",
                        "dropType": "NORMAL"
                    },
                    {
                        "occPercent": "OFTEN",
                        "type": "MATERIAL",
                        "id": "30061",
                        "dropType": "NORMAL"
                    },
                    {
                        "occPercent": "OFTEN",
                        "type": "MATERIAL",
                        "id": "30041",
                        "dropType": "NORMAL"
                    },
                    {
                        "occPercent": "OFTEN",
                        "type": "MATERIAL",
                        "id": "30051",
                        "dropType": "NORMAL"
                    },
                    {
                        "occPercent": "OFTEN",
                        "type": "MATERIAL",
                        "id": "30021",
                        "dropType": "NORMAL"
                    },
                    {
                        "occPercent": "USUAL",
                        "type": "MATERIAL",
                        "id": "30011",
                        "dropType": "NORMAL"
                    },
                    {
                        "occPercent": "ALWAYS",
                        "type": "DIAMOND",
                        "id": "4002",
                        "dropType": "COMPLETE"
                    }
                ]
            },
            "canUseCharm": false,
            "canUseTech": false,
            "canUseTrapTool": false,
            "canUseBattlePerformance": false,
            "startButtonOverrideId": null,
            "isStagePatch": false,
            "mainStageId": "act13mini_01",
            "extraCondition": null,
            "extraInfo": null
        },
        {
            "stageType": "ACTIVITY",
            "difficulty": "FOUR_STAR",
            "performanceStageFlag": "NORMAL_STAGE",
            "diffGroup": "NONE",
            "unlockCondition": [
                {
                    "stageId": "main_02-08",
                    "completeState": "PASS"
                },
                {
                    "stageId": "act13mini_01",
                    "completeState": "COMPLETE"
                }
            ],
            "stageId": "act13mini_01#f#",
            "levelId": "Activities/act13mini/level_act13mini_01",
            "zoneId": "act13mini_zone1",
            "code": "BW-1",
            "name": "\u5371\u697c\u6e10\u6e83",
            "description": "<@lv.fs>\u9644\u52a0\u6761\u4ef6\uff1a</>\\n\u654c\u4eba\u91cd\u91cf\u5927\u5e45\u5ea6\u63d0\u5347",
            "hardStagedId": null,
            "dangerLevel": "-",
            "dangerPoint": -1.0,
            "loadingPicId": "loading2",
            "canPractice": true,
            "canBattleReplay": false,
            "apCost": 9,
            "apFailReturn": 4,
            "etItemId": null,
            "etCost": -1,
            "etFailReturn": -1,
            "etButtonStyle": null,
            "apProtectTimes": 0,
            "diamondOnceDrop": 1,
            "practiceTicketCost": 3,
            "dailyStageDifficulty": 0,
            "expGain": 90,
            "goldGain": 90,
            "loseExpGain": 0,
            "loseGoldGain": 0,
            "passFavor": 4,
            "completeFavor": 9,
            "slProgress": 0,
            "displayMainItem": null,
            "hilightMark": false,
            "bossMark": false,
            "isPredefined": false,
            "isHardPredefined": false,
            "isSkillSelectablePredefined": false,
            "isStoryOnly": false,
            "appearanceStyle": "MAIN_NORMAL",
            "stageDropInfo": {
                "firstPassRewards": null,
                "firstCompleteRewards": null,
                "passRewards": null,
                "completeRewards": null,
                "displayRewards": [
                    {
                        "type": "ACTIVITY_ITEM",
                        "id": "act13mini_token_can",
                        "dropType": "ONCE"
                    },
                    {
                        "type": "DIAMOND",
                        "id": "4002",
                        "dropType": "COMPLETE"
                    }
                ],
                "displayDetailRewards": [
                    {
                        "occPercent": "ALWAYS",
                        "type": "ACTIVITY_ITEM",
                        "id": "act13mini_token_can",
                        "dropType": "ONCE"
                    },
                    {
                        "occPercent": "ALWAYS",
                        "type": "DIAMOND",
                        "id": "4002",
                        "dropType": "COMPLETE"
                    }
                ]
            },
            "canUseCharm": false,
            "canUseTech": false,
            "canUseTrapTool": false,
            "canUseBattlePerformance": false,
            "startButtonOverrideId": null,
            "isStagePatch": false,
            "mainStageId": "act13mini_01",
            "extraCondition": null,
            "extraInfo": null
        },
        {
            "stageType": "ACTIVITY",
            "difficulty": "NORMAL",
            "performanceStageFlag": "NORMAL_STAGE",
            "diffGroup": "NONE",
            "unlockCondition": [
                {
                    "stageId": "act13mini_01",
                    "completeState": "PASS"
                }
            ],
            "stageId": "act13mini_02",
            "levelId": "Activities/act13mini/level_act13mini_02",
            "zoneId": "act13mini_zone1",
            "code": "BW-2",
            "name": "\u51b7\u7bad\u7099\u5f39",
            "description": "\u4e0d\u8981\u88ab\u773c\u524d\u6d8c\u6765\u7684\u7fa4\u866b\u906e\u853d\u89c6\u7ebf\uff0c\u90a3\u4e9b\u5f13\u5f29\u4e0e\u70ae\u7b52\u6b63\u4ece\u8fdc\u65b9\u7f13\u7f13\u7784\u51c6\u4f60\u7684\u9632\u7ebf\u3002",
            "hardStagedId": "act13mini_02#f#",
            "dangerLevel": "\u7cbe\u82f11 LV.1",
            "dangerPoint": -1.0,
            "loadingPicId": "loading3",
            "canPractice": true,
            "canBattleReplay": true,
            "apCost": 9,
            "apFailReturn": 8,
            "etItemId": null,
            "etCost": -1,
            "etFailReturn": -1,
            "etButtonStyle": null,
            "apProtectTimes": 1,
            "diamondOnceDrop": 1,
            "practiceTicketCost": 1,
            "dailyStageDifficulty": 0,
            "expGain": 90,
            "goldGain": 90,
            "loseExpGain": 0,
            "loseGoldGain": 0,
            "passFavor": 8,
            "completeFavor": 9,
            "slProgress": 0,
            "displayMainItem": null,
            "hilightMark": false,
            "bossMark": false,
            "isPredefined": false,
            "isHardPredefined": false,
            "isSkillSelectablePredefined": false,
            "isStoryOnly": false,
            "appearanceStyle": "MAIN_NORMAL",
            "stageDropInfo": {
                "firstPassRewards": null,
                "firstCompleteRewards": null,
                "passRewards": null,
                "completeRewards": null,
                "displayRewards": [
                    {
                        "type": "ACTIVITY_ITEM",
                        "id": "act13mini_token_can",
                        "dropType": "COMPLETE"
                    },
                    {
                        "type": "ACTIVITY_ITEM",
                        "id": "act13mini_token_can",
                        "dropType": "SPECIAL"
                    },
                    {
                        "type": "MATERIAL",
                        "id": "30031",
                        "dropType": "NORMAL"
                    },
                    {
                        "type": "MATERIAL",
                        "id": "30061",
                        "dropType": "NORMAL"
                    },
                    {
                        "type": "MATERIAL",
                        "id": "30041",
                        "dropType": "NORMAL"
                    },
                    {
                        "type": "MATERIAL",
                        "id": "30051",
                        "dropType": "NORMAL"
                    },
                    {
                        "type": "MATERIAL",
                        "id": "30021",
                        "dropType": "NORMAL"
                    },
                    {
                        "type": "MATERIAL",
                        "id": "30011",
                        "dropType": "NORMAL"
                    },
                    {
                        "type": "DIAMOND",
                        "id": "4002",
                        "dropType": "COMPLETE"
                    }
                ],
                "displayDetailRewards": [
                    {
                        "occPercent": "ALWAYS",
                        "type": "ACTIVITY_ITEM",
                        "id": "act13mini_token_can",
                        "dropType": "COMPLETE"
                    },
                    {
                        "occPercent": "ALWAYS",
                        "type": "ACTIVITY_ITEM",
                        "id": "act13mini_token_can",
                        "dropType": "SPECIAL"
                    },
                    {
                        "occPercent": "OFTEN",
                        "type": "MATERIAL",
                        "id": "30031",
                        "dropType": "NORMAL"
                    },
                    {
                        "occPercent": "OFTEN",
                        "type": "MATERIAL",
                        "id": "30061",
                        "dropType": "NORMAL"
                    },
                    {
                        "occPercent": "OFTEN",
                        "type": "MATERIAL",
                        "id": "30041",
                        "dropType": "NORMAL"
                    },
                    {
                        "occPercent": "OFTEN",
                        "type": "MATERIAL",
                        "id": "30051",
                        "dropType": "NORMAL"
                    },
                    {
                        "occPercent": "OFTEN",
                        "type": "MATERIAL",
                        "id": "30021",
                        "dropType": "NORMAL"
                    },
                    {
                        "occPercent": "USUAL",
                        "type": "MATERIAL",
                        "id": "30011",
                        "dropType": "NORMAL"
                    },
                    {
                        "occPercent": "ALWAYS",
                        "type": "DIAMOND",
                        "id": "4002",
                        "dropType": "COMPLETE"
                    }
                ]
            },
            "canUseCharm": false,
            "canUseTech": false,
            "canUseTrapTool": false,
            "canUseBattlePerformance": false,
            "startButtonOverrideId": null,
            "isStagePatch": false,
            "mainStageId": "act13mini_01",
            "extraCondition": null,
            "extraInfo": null
        },
        {
            "stageType": "ACTIVITY",
            "difficulty": "FOUR_STAR",
            "performanceStageFlag": "NORMAL_STAGE",
            "diffGroup": "NONE",
            "unlockCondition": [
                {
                    "stageId": "main_02-08",
                    "completeState": "PASS"
                },
                {
                    "stageId": "act13mini_02",
                    "completeState": "COMPLETE"
                }
            ],
            "stageId": "act13mini_02#f#",
            "levelId": "Activities/act13mini/level_act13mini_02",
            "zoneId": "act13mini_zone1",
            "code": "BW-2",
            "name": "\u51b7\u7bad\u7099\u5f39",
            "description": "<@lv.fs>\u9644\u52a0\u6761\u4ef6\uff1a</>\\n\u91cd\u88c5\u548c\u7279\u79cd\u5e72\u5458\u90e8\u7f72\u8d39\u7528\u53d8\u4e3a2\u500d",
            "hardStagedId": null,
            "dangerLevel": "-",
            "dangerPoint": -1.0,
            "loadingPicId": "loading3",
            "canPractice": true,
            "canBattleReplay": false,
            "apCost": 9,
            "apFailReturn": 4,
            "etItemId": null,
            "etCost": -1,
            "etFailReturn": -1,
            "etButtonStyle": null,
            "apProtectTimes": 0,
            "diamondOnceDrop": 1,
            "practiceTicketCost": 3,
            "dailyStageDifficulty": 0,
            "expGain": 90,
            "goldGain": 90,
            "loseExpGain": 0,
            "loseGoldGain": 0,
            "passFavor": 4,
            "completeFavor": 9,
            "slProgress": 0,
            "displayMainItem": null,
            "hilightMark": false,
            "bossMark": false,
            "isPredefined": false,
            "isHardPredefined": false,
            "isSkillSelectablePredefined": false,
            "isStoryOnly": false,
            "appearanceStyle": "MAIN_NORMAL",
            "stageDropInfo": {
                "firstPassRewards": null,
                "firstCompleteRewards": null,
                "passRewards": null,
                "completeRewards": null,
                "displayRewards": [
                    {
                        "type": "ACTIVITY_ITEM",
                        "id": "act13mini_token_can",
                        "dropType": "ONCE"
                    },
                    {
                        "type": "DIAMOND",
                        "id": "4002",
                        "dropType": "COMPLETE"
                    }
                ],
                "displayDetailRewards": [
                    {
                        "occPercent": "ALWAYS",
                        "type": "ACTIVITY_ITEM",
                        "id": "act13mini_token_can",
                        "dropType": "ONCE"
                    },
                    {
                        "occPercent": "ALWAYS",
                        "type": "DIAMOND",
                        "id": "4002",
                        "dropType": "COMPLETE"
                    }
                ]
            },
            "canUseCharm": false,
            "canUseTech": false,
            "canUseTrapTool": false,
            "canUseBattlePerformance": false,
            "startButtonOverrideId": null,
            "isStagePatch": false,
            "mainStageId": "act13mini_01",
            "extraCondition": null,
            "extraInfo": null
        },
        {
            "stageType": "ACTIVITY",
            "difficulty": "NORMAL",
            "performanceStageFlag": "NORMAL_STAGE",
            "diffGroup": "NONE",
            "unlockCondition": [
                {
                    "stageId": "act13mini_02",
                    "completeState": "PASS"
                }
            ],
            "stageId": "act13mini_03",
            "levelId": "Activities/act13mini/level_act13mini_03",
            "zoneId": "act13mini_zone1",
            "code": "BW-3",
            "name": "\u6b67\u8def\u5f77\u5fa8",
            "description": "\u90a3\u4e9b\u6f2b\u65e0\u76ee\u6807\u7684\u5954\u6ce2\u4e4b\u4eba\uff0c\u8bf7\u4f60\u9a7b\u8db3\u3002",
            "hardStagedId": "act13mini_03#f#",
            "dangerLevel": "\u7cbe\u82f11 LV.35",
            "dangerPoint": -1.0,
            "loadingPicId": "loading3",
            "canPractice": true,
            "canBattleReplay": true,
            "apCost": 12,
            "apFailReturn": 11,
            "etItemId": null,
            "etCost": -1,
            "etFailReturn": -1,
            "etButtonStyle": null,
            "apProtectTimes": 1,
            "diamondOnceDrop": 1,
            "practiceTicketCost": 1,
            "dailyStageDifficulty": 0,
            "expGain": 120,
            "goldGain": 120,
            "loseExpGain": 0,
            "loseGoldGain": 0,
            "passFavor": 11,
            "completeFavor": 12,
            "slProgress": 0,
            "displayMainItem": null,
            "hilightMark": false,
            "bossMark": false,
            "isPredefined": false,
            "isHardPredefined": false,
            "isSkillSelectablePredefined": false,
            "isStoryOnly": false,
            "appearanceStyle": "MAIN_NORMAL",
            "stageDropInfo": {
                "firstPassRewards": null,
                "firstCompleteRewards": null,
                "passRewards": null,
                "completeRewards": null,
                "displayRewards": [
                    {
                        "type": "ACTIVITY_ITEM",
                        "id": "act13mini_token_can",
                        "dropType": "COMPLETE"
                    },
                    {
                        "type": "ACTIVITY_ITEM",
                        "id": "act13mini_token_can",
                        "dropType": "SPECIAL"
                    },
                    {
                        "type": "MATERIAL",
                        "id": "30031",
                        "dropType": "NORMAL"
                    },
                    {
                        "type": "MATERIAL",
                        "id": "30061",
                        "dropType": "NORMAL"
                    },
                    {
                        "type": "MATERIAL",
                        "id": "30041",
                        "dropType": "NORMAL"
                    },
                    {
                        "type": "MATERIAL",
                        "id": "30051",
                        "dropType": "NORMAL"
                    },
                    {
                        "type": "MATERIAL",
                        "id": "30021",
                        "dropType": "NORMAL"
                    },
                    {
                        "type": "MATERIAL",
                        "id": "30011",
                        "dropType": "NORMAL"
                    },
                    {
                        "type": "DIAMOND",
                        "id": "4002",
                        "dropType": "COMPLETE"
                    }
                ],
                "displayDetailRewards": [
                    {
                        "occPercent": "ALWAYS",
                        "type": "ACTIVITY_ITEM",
                        "id": "act13mini_token_can",
                        "dropType": "COMPLETE"
                    },
                    {
                        "occPercent": "ALWAYS",
                        "type": "ACTIVITY_ITEM",
                        "id": "act13mini_token_can",
                        "dropType": "SPECIAL"
                    },
                    {
                        "occPercent": "USUAL",
                        "type": "MATERIAL",
                        "id": "30031",
                        "dropType": "NORMAL"
                    },
                    {
                        "occPercent": "OFTEN",
                        "type": "MATERIAL",
                        "id": "30061",
                        "dropType": "NORMAL"
                    },
                    {
                        "occPercent": "OFTEN",
                        "type": "MATERIAL",
                        "id": "30041",
                        "dropType": "NORMAL"
                    },
                    {
                        "occPercent": "OFTEN",
                        "type": "MATERIAL",
                        "id": "30051",
                        "dropType": "NORMAL"
                    },
                    {
                        "occPercent": "USUAL",
                        "type": "MATERIAL",
                        "id": "30021",
                        "dropType": "NORMAL"
                    },
                    {
                        "occPercent": "ALMOST",
                        "type": "MATERIAL",
                        "id": "30011",
                        "dropType": "NORMAL"
                    },
                    {
                        "occPercent": "ALWAYS",
                        "type": "DIAMOND",
                        "id": "4002",
                        "dropType": "COMPLETE"
                    }
                ]
            },
            "canUseCharm": false,
            "canUseTech": false,
            "canUseTrapTool": false,
            "canUseBattlePerformance": false,
            "startButtonOverrideId": null,
            "isStagePatch": false,
            "mainStageId": "act13mini_01",
            "extraCondition": null,
            "extraInfo": null
        },
        {
            "stageType": "ACTIVITY",
            "difficulty": "FOUR_STAR",
            "performanceStageFlag": "NORMAL_STAGE",
            "diffGroup": "NONE",
            "unlockCondition": [
                {
                    "stageId": "main_02-08",
                    "completeState": "PASS"
                },
                {
                    "stageId": "act13mini_03",
                    "completeState": "COMPLETE"
                }
            ],
            "stageId": "act13mini_03#f#",
            "levelId": "Activities/act13mini/level_act13mini_03",
            "zoneId": "act13mini_zone1",
            "code": "BW-3",
            "name": "\u6b67\u8def\u5f77\u5fa8",
            "description": "<@lv.fs>\u9644\u52a0\u6761\u4ef6\uff1a</>\\n\u8428\u5361\u5179\u9b54\u5251\u7ec4\u957f\u53d8\u4e3a\u8428\u5361\u5179\u79ef\u6028\u8005",
            "hardStagedId": null,
            "dangerLevel": "-",
            "dangerPoint": -1.0,
            "loadingPicId": "loading3",
            "canPractice": true,
            "canBattleReplay": false,
            "apCost": 12,
            "apFailReturn": 6,
            "etItemId": null,
            "etCost": -1,
            "etFailReturn": -1,
            "etButtonStyle": null,
            "apProtectTimes": 0,
            "diamondOnceDrop": 1,
            "practiceTicketCost": 3,
            "dailyStageDifficulty": 0,
            "expGain": 120,
            "goldGain": 120,
            "loseExpGain": 0,
            "loseGoldGain": 0,
            "passFavor": 6,
            "completeFavor": 12,
            "slProgress": 0,
            "displayMainItem": null,
            "hilightMark": false,
            "bossMark": false,
            "isPredefined": false,
            "isHardPredefined": false,
            "isSkillSelectablePredefined": false,
            "isStoryOnly": false,
            "appearanceStyle": "MAIN_NORMAL",
            "stageDropInfo": {
                "firstPassRewards": null,
                "firstCompleteRewards": null,
                "passRewards": null,
                "completeRewards": null,
                "displayRewards": [
                    {
                        "type": "ACTIVITY_ITEM",
                        "id": "act13mini_token_can",
                        "dropType": "ONCE"
                    },
                    {
                        "type": "DIAMOND",
                        "id": "4002",
                        "dropType": "COMPLETE"
                    }
                ],
                "displayDetailRewards": [
                    {
                        "occPercent": "ALWAYS",
                        "type": "ACTIVITY_ITEM",
                        "id": "act13mini_token_can",
                        "dropType": "ONCE"
                    },
                    {
                        "occPercent": "ALWAYS",
                        "type": "DIAMOND",
                        "id": "4002",
                        "dropType": "COMPLETE"
                    }
                ]
            },
            "canUseCharm": false,
            "canUseTech": false,
            "canUseTrapTool": false,
            "canUseBattlePerformance": false,
            "startButtonOverrideId": null,
            "isStagePatch": false,
            "mainStageId": "act13mini_01",
            "extraCondition": null,
            "extraInfo": null
        },
        {
            "stageType": "ACTIVITY",
            "difficulty": "NORMAL",
            "performanceStageFlag": "NORMAL_STAGE",
            "diffGroup": "NONE",
            "unlockCondition": [
                {
                    "stageId": "act13mini_03",
                    "completeState": "PASS"
                }
            ],
            "stageId": "act13mini_04",
            "levelId": "Activities/act13mini/level_act13mini_04",
            "zoneId": "act13mini_zone1",
            "code": "BW-4",
            "name": "\u9713\u8679\u4e4b\u591c",
            "description": "\u88ab\u9713\u8679\u706f\u6e32\u67d3\u8fc7\u7684\u6591\u9a73\u591c\u665a\u4e2d\uff0c\u4e00\u4e9b\u55a7\u95f9\u548c\u52a8\u8361\u6084\u7136\u6ecb\u751f\u3002\\n<@lv.rem><\u6307\u6325\u7ec8\u7aef></>\u88ab\u6467\u6bc1\u65f6\u62631\u70b9\u5173\u5361\u751f\u547d\u503c",
            "hardStagedId": "act13mini_04#f#",
            "dangerLevel": "\u7cbe\u82f11 LV.70",
            "dangerPoint": -1.0,
            "loadingPicId": "loading_PL_Downtown",
            "canPractice": true,
            "canBattleReplay": true,
            "apCost": 12,
            "apFailReturn": 11,
            "etItemId": null,
            "etCost": -1,
            "etFailReturn": -1,
            "etButtonStyle": null,
            "apProtectTimes": 1,
            "diamondOnceDrop": 1,
            "practiceTicketCost": 1,
            "dailyStageDifficulty": 0,
            "expGain": 120,
            "goldGain": 120,
            "loseExpGain": 0,
            "loseGoldGain": 0,
            "passFavor": 11,
            "completeFavor": 12,
            "slProgress": 0,
            "displayMainItem": null,
            "hilightMark": false,
            "bossMark": false,
            "isPredefined": false,
            "isHardPredefined": false,
            "isSkillSelectablePredefined": false,
            "isStoryOnly": false,
            "appearanceStyle": "MAIN_NORMAL",
            "stageDropInfo": {
                "firstPassRewards": null,
                "firstCompleteRewards": null,
                "passRewards": null,
                "completeRewards": null,
                "displayRewards": [
                    {
                        "type": "ACTIVITY_ITEM",
                        "id": "act13mini_token_can",
                        "dropType": "COMPLETE"
                    },
                    {
                        "type": "ACTIVITY_ITEM",
                        "id": "act13mini_token_can",
                        "dropType": "SPECIAL"
                    },
                    {
                        "type": "MATERIAL",
                        "id": "30031",
                        "dropType": "NORMAL"
                    },
                    {
                        "type": "MATERIAL",
                        "id": "30061",
                        "dropType": "NORMAL"
                    },
                    {
                        "type": "MATERIAL",
                        "id": "30041",
                        "dropType": "NORMAL"
                    },
                    {
                        "type": "MATERIAL",
                        "id": "30051",
                        "dropType": "NORMAL"
                    },
                    {
                        "type": "MATERIAL",
                        "id": "30021",
                        "dropType": "NORMAL"
                    },
                    {
                        "type": "MATERIAL",
                        "id": "30011",
                        "dropType": "NORMAL"
                    },
                    {
                        "type": "DIAMOND",
                        "id": "4002",
                        "dropType": "COMPLETE"
                    }
                ],
                "displayDetailRewards": [
                    {
                        "occPercent": "ALWAYS",
                        "type": "ACTIVITY_ITEM",
                        "id": "act13mini_token_can",
                        "dropType": "COMPLETE"
                    },
                    {
                        "occPercent": "ALWAYS",
                        "type": "ACTIVITY_ITEM",
                        "id": "act13mini_token_can",
                        "dropType": "SPECIAL"
                    },
                    {
                        "occPercent": "USUAL",
                        "type": "MATERIAL",
                        "id": "30031",
                        "dropType": "NORMAL"
                    },
                    {
                        "occPercent": "OFTEN",
                        "type": "MATERIAL",
                        "id": "30061",
                        "dropType": "NORMAL"
                    },
                    {
                        "occPercent": "OFTEN",
                        "type": "MATERIAL",
                        "id": "30041",
                        "dropType": "NORMAL"
                    },
                    {
                        "occPercent": "OFTEN",
                        "type": "MATERIAL",
                        "id": "30051",
                        "dropType": "NORMAL"
                    },
                    {
                        "occPercent": "USUAL",
                        "type": "MATERIAL",
                        "id": "30021",
                        "dropType": "NORMAL"
                    },
                    {
                        "occPercent": "ALMOST",
                        "type": "MATERIAL",
                        "id": "30011",
                        "dropType": "NORMAL"
                    },
                    {
                        "occPercent": "ALWAYS",
                        "type": "DIAMOND",
                        "id": "4002",
                        "dropType": "COMPLETE"
                    }
                ]
            },
            "canUseCharm": false,
            "canUseTech": false,
            "canUseTrapTool": false,
            "canUseBattlePerformance": false,
            "startButtonOverrideId": null,
            "isStagePatch": false,
            "mainStageId": "act13mini_01",
            "extraCondition": null,
            "extraInfo": null
        },
        {
            "stageType": "ACTIVITY",
            "difficulty": "FOUR_STAR",
            "performanceStageFlag": "NORMAL_STAGE",
            "diffGroup": "NONE",
            "unlockCondition": [
                {
                    "stageId": "main_02-08",
                    "completeState": "PASS"
                },
                {
                    "stageId": "act13mini_04",
                    "completeState": "COMPLETE"
                }
            ],
            "stageId": "act13mini_04#f#",
            "levelId": "Activities/act13mini/level_act13mini_04",
            "zoneId": "act13mini_zone1",
            "code": "BW-4",
            "name": "\u9713\u8679\u4e4b\u591c",
            "description": "<@lv.fs>\u9644\u52a0\u6761\u4ef6\uff1a</>\\n\u6b3a\u51cc\u8005\u83b7\u5f97\u9690\u533f",
            "hardStagedId": null,
            "dangerLevel": "-",
            "dangerPoint": -1.0,
            "loadingPicId": "loading_PL_Downtown",
            "canPractice": true,
            "canBattleReplay": false,
            "apCost": 12,
            "apFailReturn": 6,
            "etItemId": null,
            "etCost": -1,
            "etFailReturn": -1,
            "etButtonStyle": null,
            "apProtectTimes": 0,
            "diamondOnceDrop": 1,
            "practiceTicketCost": 3,
            "dailyStageDifficulty": 0,
            "expGain": 120,
            "goldGain": 120,
            "loseExpGain": 0,
            "loseGoldGain": 0,
            "passFavor": 6,
            "completeFavor": 12,
            "slProgress": 0,
            "displayMainItem": null,
            "hilightMark": false,
            "bossMark": false,
            "isPredefined": false,
            "isHardPredefined": false,
            "isSkillSelectablePredefined": false,
            "isStoryOnly": false,
            "appearanceStyle": "MAIN_NORMAL",
            "stageDropInfo": {
                "firstPassRewards": null,
                "firstCompleteRewards": null,
                "passRewards": null,
                "completeRewards": null,
                "displayRewards": [
                    {
                        "type": "ACTIVITY_ITEM",
                        "id": "act13mini_token_can",
                        "dropType": "ONCE"
                    },
                    {
                        "type": "DIAMOND",
                        "id": "4002",
                        "dropType": "COMPLETE"
                    }
                ],
                "displayDetailRewards": [
                    {
                        "occPercent": "ALWAYS",
                        "type": "ACTIVITY_ITEM",
                        "id": "act13mini_token_can",
                        "dropType": "ONCE"
                    },
                    {
                        "occPercent": "ALWAYS",
                        "type": "DIAMOND",
                        "id": "4002",
                        "dropType": "COMPLETE"
                    }
                ]
            },
            "canUseCharm": false,
            "canUseTech": false,
            "canUseTrapTool": false,
            "canUseBattlePerformance": false,
            "startButtonOverrideId": null,
            "isStagePatch": false,
            "mainStageId": "act13mini_01",
            "extraCondition": null,
            "extraInfo": null
        },
        {
            "stageType": "ACTIVITY",
            "difficulty": "NORMAL",
            "performanceStageFlag": "NORMAL_STAGE",
            "diffGroup": "NONE",
            "unlockCondition": [
                {
                    "stageId": "act13mini_04",
                    "completeState": "PASS"
                }
            ],
            "stageId": "act13mini_05",
            "levelId": "Activities/act13mini/level_act13mini_05",
            "zoneId": "act13mini_zone1",
            "code": "BW-5",
            "name": "\u4e00\u592b\u5f53\u5173",
            "description": "\u65e0\u8bba\u662f\u5e94\u654c\u8fd8\u662f\u4e89\u52bf\uff0c\u90fd\u8981\u62ff\u634f\u4f4f\u54bd\u5589\u624d\u597d\u3002",
            "hardStagedId": "act13mini_05#f#",
            "dangerLevel": "\u7cbe\u82f12 LV.1",
            "dangerPoint": -1.0,
            "loadingPicId": "loading_LM_night",
            "canPractice": true,
            "canBattleReplay": true,
            "apCost": 15,
            "apFailReturn": 14,
            "etItemId": null,
            "etCost": -1,
            "etFailReturn": -1,
            "etButtonStyle": null,
            "apProtectTimes": 1,
            "diamondOnceDrop": 1,
            "practiceTicketCost": 1,
            "dailyStageDifficulty": 0,
            "expGain": 150,
            "goldGain": 150,
            "loseExpGain": 0,
            "loseGoldGain": 0,
            "passFavor": 14,
            "completeFavor": 15,
            "slProgress": 0,
            "displayMainItem": null,
            "hilightMark": false,
            "bossMark": false,
            "isPredefined": false,
            "isHardPredefined": false,
            "isSkillSelectablePredefined": false,
            "isStoryOnly": false,
            "appearanceStyle": "MAIN_NORMAL",
            "stageDropInfo": {
                "firstPassRewards": null,
                "firstCompleteRewards": null,
                "passRewards": null,
                "completeRewards": null,
                "displayRewards": [
                    {
                        "type": "ACTIVITY_ITEM",
                        "id": "act13mini_token_can",
                        "dropType": "COMPLETE"
                    },
                    {
                        "type": "ACTIVITY_ITEM",
                        "id": "act13mini_token_can",
                        "dropType": "SPECIAL"
                    },
                    {
                        "type": "MATERIAL",
                        "id": "30052",
                        "dropType": "NORMAL"
                    },
                    {
                        "type": "DIAMOND",
                        "id": "4002",
                        "dropType": "COMPLETE"
                    }
                ],
                "displayDetailRewards": [
                    {
                        "occPercent": "ALWAYS",
                        "type": "ACTIVITY_ITEM",
                        "id": "act13mini_token_can",
                        "dropType": "COMPLETE"
                    },
                    {
                        "occPercent": "ALWAYS",
                        "type": "ACTIVITY_ITEM",
                        "id": "act13mini_token_can",
                        "dropType": "SPECIAL"
                    },
                    {
                        "occPercent": "ALWAYS",
                        "type": "MATERIAL",
                        "id": "30052",
                        "dropType": "NORMAL"
                    },
                    {
                        "occPercent": "OFTEN",
                        "type": "MATERIAL",
                        "id": "30011",
                        "dropType": "ADDITIONAL"
                    },
                    {
                        "occPercent": "SOMETIMES",
                        "type": "MATERIAL",
                        "id": "30031",
                        "dropType": "ADDITIONAL"
                    },
                    {
                        "occPercent": "SOMETIMES",
                        "type": "MATERIAL",
                        "id": "30061",
                        "dropType": "ADDITIONAL"
                    },
                    {
                        "occPercent": "SOMETIMES",
                        "type": "MATERIAL",
                        "id": "3003",
                        "dropType": "ADDITIONAL"
                    },
                    {
                        "occPercent": "OFTEN",
                        "type": "MATERIAL",
                        "id": "30012",
                        "dropType": "ADDITIONAL"
                    },
                    {
                        "occPercent": "SOMETIMES",
                        "type": "MATERIAL",
                        "id": "30032",
                        "dropType": "ADDITIONAL"
                    },
                    {
                        "occPercent": "SOMETIMES",
                        "type": "MATERIAL",
                        "id": "30062",
                        "dropType": "ADDITIONAL"
                    },
                    {
                        "occPercent": "ALWAYS",
                        "type": "DIAMOND",
                        "id": "4002",
                        "dropType": "COMPLETE"
                    }
                ]
            },
            "canUseCharm": false,
            "canUseTech": false,
            "canUseTrapTool": false,
            "canUseBattlePerformance": false,
            "startButtonOverrideId": null,
            "isStagePatch": false,
            "mainStageId": "act13mini_01",
            "extraCondition": null,
            "extraInfo": null
        },
        {
            "stageType": "ACTIVITY",
            "difficulty": "FOUR_STAR",
            "performanceStageFlag": "NORMAL_STAGE",
            "diffGroup": "NONE",
            "unlockCondition": [
                {
                    "stageId": "main_02-08",
                    "completeState": "PASS"
                },
                {
                    "stageId": "act13mini_05",
                    "completeState": "COMPLETE"
                }
            ],
            "stageId": "act13mini_05#f#",
            "levelId": "Activities/act13mini/level_act13mini_05",
            "zoneId": "act13mini_zone1",
            "code": "BW-5",
            "name": "\u4e00\u592b\u5f53\u5173",
            "description": "<@lv.fs>\u9644\u52a0\u6761\u4ef6\uff1a</>\\n\u590d\u4ec7\u8005\u653b\u51fb\u529b\u5927\u5e45\u63d0\u5347",
            "hardStagedId": null,
            "dangerLevel": "-",
            "dangerPoint": -1.0,
            "loadingPicId": "loading_LM_night",
            "canPractice": true,
            "canBattleReplay": false,
            "apCost": 15,
            "apFailReturn": 7,
            "etItemId": null,
            "etCost": -1,
            "etFailReturn": -1,
            "etButtonStyle": null,
            "apProtectTimes": 0,
            "diamondOnceDrop": 1,
            "practiceTicketCost": 3,
            "dailyStageDifficulty": 0,
            "expGain": 150,
            "goldGain": 150,
            "loseExpGain": 0,
            "loseGoldGain": 0,
            "passFavor": 7,
            "completeFavor": 15,
            "slProgress": 0,
            "displayMainItem": null,
            "hilightMark": false,
            "bossMark": false,
            "isPredefined": false,
            "isHardPredefined": false,
            "isSkillSelectablePredefined": false,
            "isStoryOnly": false,
            "appearanceStyle": "MAIN_NORMAL",
            "stageDropInfo": {
                "firstPassRewards": null,
                "firstCompleteRewards": null,
                "passRewards": null,
                "completeRewards": null,
                "displayRewards": [
                    {
                        "type": "ACTIVITY_ITEM",
                        "id": "act13mini_token_can",
                        "dropType": "ONCE"
                    },
                    {
                        "type": "DIAMOND",
                        "id": "4002",
                        "dropType": "COMPLETE"
                    }
                ],
                "displayDetailRewards": [
                    {
                        "occPercent": "ALWAYS",
                        "type": "ACTIVITY_ITEM",
                        "id": "act13mini_token_can",
                        "dropType": "ONCE"
                    },
                    {
                        "occPercent": "ALWAYS",
                        "type": "DIAMOND",
                        "id": "4002",
                        "dropType": "COMPLETE"
                    }
                ]
            },
            "canUseCharm": false,
            "canUseTech": false,
            "canUseTrapTool": false,
            "canUseBattlePerformance": false,
            "startButtonOverrideId": null,
            "isStagePatch": false,
            "mainStageId": "act13mini_01",
            "extraCondition": null,
            "extraInfo": null
        },
        {
            "stageType": "ACTIVITY",
            "difficulty": "NORMAL",
            "performanceStageFlag": "NORMAL_STAGE",
            "diffGroup": "NONE",
            "unlockCondition": [
                {
                    "stageId": "act13mini_05",
                    "completeState": "PASS"
                }
            ],
            "stageId": "act13mini_06",
            "levelId": "Activities/act13mini/level_act13mini_06",
            "zoneId": "act13mini_zone1",
            "code": "BW-6",
            "name": "\u96e8\u4e2d\u8703\u666f",
            "description": "\u74e2\u6cfc\u5927\u96e8\u626d\u66f2\u4e86\u4f60\u773c\u4e2d\u7684\u8857\u9053\uff0c\u51e0\u9053\u8703\u5f71\u4ece\u73b0\u5b9e\u4e0e\u865a\u5e7b\u7684\u5939\u7f1d\u4e2d\u56db\u6563\u800c\u51fa\u3002\\n<@lv.item><\u6666\u660e\u4e4b\u5370></>\u90e8\u7f72\u5728\u5176\u4e0a\u7684\u5e72\u5458\u83b7\u5f97\u6666\u660e\u5c5e\u6027\\n<@lv.item><\u671d\u66ae\u4e4b\u5370></>\u654c\u4eba\u9996\u6b21\u7ecf\u8fc7\u540e\u5c5e\u6027\u53d8\u5316",
            "hardStagedId": "act13mini_06#f#",
            "dangerLevel": "\u7cbe\u82f12 LV.10",
            "dangerPoint": -1.0,
            "loadingPicId": "loading_Painting_Day",
            "canPractice": true,
            "canBattleReplay": true,
            "apCost": 15,
            "apFailReturn": 14,
            "etItemId": null,
            "etCost": -1,
            "etFailReturn": -1,
            "etButtonStyle": null,
            "apProtectTimes": 1,
            "diamondOnceDrop": 1,
            "practiceTicketCost": 1,
            "dailyStageDifficulty": 0,
            "expGain": 150,
            "goldGain": 150,
            "loseExpGain": 0,
            "loseGoldGain": 0,
            "passFavor": 14,
            "completeFavor": 15,
            "slProgress": 0,
            "displayMainItem": null,
            "hilightMark": false,
            "bossMark": false,
            "isPredefined": false,
            "isHardPredefined": false,
            "isSkillSelectablePredefined": false,
            "isStoryOnly": false,
            "appearanceStyle": "MAIN_NORMAL",
            "stageDropInfo": {
                "firstPassRewards": null,
                "firstCompleteRewards": null,
                "passRewards": null,
                "completeRewards": null,
                "displayRewards": [
                    {
                        "type": "ACTIVITY_ITEM",
                        "id": "act13mini_token_can",
                        "dropType": "COMPLETE"
                    },
                    {
                        "type": "ACTIVITY_ITEM",
                        "id": "act13mini_token_can",
                        "dropType": "SPECIAL"
                    },
                    {
                        "type": "MATERIAL",
                        "id": "30022",
                        "dropType": "NORMAL"
                    },
                    {
                        "type": "DIAMOND",
                        "id": "4002",
                        "dropType": "COMPLETE"
                    }
                ],
                "displayDetailRewards": [
                    {
                        "occPercent": "ALWAYS",
                        "type": "ACTIVITY_ITEM",
                        "id": "act13mini_token_can",
                        "dropType": "COMPLETE"
                    },
                    {
                        "occPercent": "ALWAYS",
                        "type": "ACTIVITY_ITEM",
                        "id": "act13mini_token_can",
                        "dropType": "SPECIAL"
                    },
                    {
                        "occPercent": "ALWAYS",
                        "type": "MATERIAL",
                        "id": "30022",
                        "dropType": "NORMAL"
                    },
                    {
                        "occPercent": "SOMETIMES",
                        "type": "MATERIAL",
                        "id": "30021",
                        "dropType": "ADDITIONAL"
                    },
                    {
                        "occPercent": "SOMETIMES",
                        "type": "MATERIAL",
                        "id": "30041",
                        "dropType": "ADDITIONAL"
                    },
                    {
                        "occPercent": "SOMETIMES",
                        "type": "MATERIAL",
                        "id": "30051",
                        "dropType": "ADDITIONAL"
                    },
                    {
                        "occPercent": "SOMETIMES",
                        "type": "CARD_EXP",
                        "id": "2001",
                        "dropType": "ADDITIONAL"
                    },
                    {
                        "occPercent": "SOMETIMES",
                        "type": "MATERIAL",
                        "id": "30022",
                        "dropType": "ADDITIONAL"
                    },
                    {
                        "occPercent": "SOMETIMES",
                        "type": "MATERIAL",
                        "id": "30042",
                        "dropType": "ADDITIONAL"
                    },
                    {
                        "occPercent": "SOMETIMES",
                        "type": "MATERIAL",
                        "id": "30052",
                        "dropType": "ADDITIONAL"
                    },
                    {
                        "occPercent": "SOMETIMES",
                        "type": "CARD_EXP",
                        "id": "2002",
                        "dropType": "ADDITIONAL"
                    },
                    {
                        "occPercent": "ALWAYS",
                        "type": "DIAMOND",
                        "id": "4002",
                        "dropType": "COMPLETE"
                    }
                ]
            },
            "canUseCharm": false,
            "canUseTech": false,
            "canUseTrapTool": false,
            "canUseBattlePerformance": false,
            "startButtonOverrideId": null,
            "isStagePatch": false,
            "mainStageId": "act13mini_01",
            "extraCondition": null,
            "extraInfo": null
        },
        {
            "stageType": "ACTIVITY",
            "difficulty": "FOUR_STAR",
            "performanceStageFlag": "NORMAL_STAGE",
            "diffGroup": "NONE",
            "unlockCondition": [
                {
                    "stageId": "main_02-08",
                    "completeState": "PASS"
                },
                {
                    "stageId": "act13mini_06",
                    "completeState": "COMPLETE"
                }
            ],
            "stageId": "act13mini_06#f#",
            "levelId": "Activities/act13mini/level_act13mini_06",
            "zoneId": "act13mini_zone1",
            "code": "BW-6",
            "name": "\u96e8\u4e2d\u8703\u666f",
            "description": "<@lv.fs>\u9644\u52a0\u6761\u4ef6\uff1a</>\\n\u8ba4\u771f\u7684\u201c\u963f\u54ac\u201d\u751f\u547d\u503c\u5927\u5e45\u63d0\u5347",
            "hardStagedId": null,
            "dangerLevel": "-",
            "dangerPoint": -1.0,
            "loadingPicId": "loading_Painting_Day",
            "canPractice": true,
            "canBattleReplay": false,
            "apCost": 15,
            "apFailReturn": 7,
            "etItemId": null,
            "etCost": -1,
            "etFailReturn": -1,
            "etButtonStyle": null,
            "apProtectTimes": 0,
            "diamondOnceDrop": 1,
            "practiceTicketCost": 3,
            "dailyStageDifficulty": 0,
            "expGain": 150,
            "goldGain": 150,
            "loseExpGain": 0,
            "loseGoldGain": 0,
            "passFavor": 7,
            "completeFavor": 15,
            "slProgress": 0,
            "displayMainItem": null,
            "hilightMark": false,
            "bossMark": false,
            "isPredefined": false,
            "isHardPredefined": false,
            "isSkillSelectablePredefined": false,
            "isStoryOnly": false,
            "appearanceStyle": "MAIN_NORMAL",
            "stageDropInfo": {
                "firstPassRewards": null,
                "firstCompleteRewards": null,
                "passRewards": null,
                "completeRewards": null,
                "displayRewards": [
                    {
                        "type": "ACTIVITY_ITEM",
                        "id": "act13mini_token_can",
                        "dropType": "ONCE"
                    },
                    {
                        "type": "DIAMOND",
                        "id": "4002",
                        "dropType": "COMPLETE"
                    }
                ],
                "displayDetailRewards": [
                    {
                        "occPercent": "ALWAYS",
                        "type": "ACTIVITY_ITEM",
                        "id": "act13mini_token_can",
                        "dropType": "ONCE"
                    },
                    {
                        "occPercent": "ALWAYS",
                        "type": "DIAMOND",
                        "id": "4002",
                        "dropType": "COMPLETE"
                    }
                ]
            },
            "canUseCharm": false,
            "canUseTech": false,
            "canUseTrapTool": false,
            "canUseBattlePerformance": false,
            "startButtonOverrideId": null,
            "isStagePatch": false,
            "mainStageId": "act13mini_01",
            "extraCondition": null,
            "extraInfo": null
        },
        {
            "stageType": "ACTIVITY",
            "difficulty": "NORMAL",
            "performanceStageFlag": "NORMAL_STAGE",
            "diffGroup": "NONE",
            "unlockCondition": [
                {
                    "stageId": "act13mini_06",
                    "completeState": "PASS"
                }
            ],
            "stageId": "act13mini_07",
            "levelId": "Activities/act13mini/level_act13mini_07",
            "zoneId": "act13mini_zone1",
            "code": "BW-7",
            "name": "\u96ea\u5929\u8def\u6ed1",
            "description": "\u5728\u51b0\u96ea\u94fa\u5c31\u7684\u8def\u9762\u4e0a\u884c\u8d70\u987b\u5f97\u5c0f\u5fc3\u7ffc\u7ffc\uff0c\u4e0d\u7136\u4e00\u5c41\u80a1\u8dcc\u5012\uff0c\u8c01\u77e5\u9053\u4f1a\u6ed1\u5411\u54ea\u91cc\u3002\\n<@lv.item><\u6e90\u77f3\u51b0\u6676></>\u5468\u671f\u6027\u5730\u91ca\u653e\u5bf9\u6211\u65b9\u5355\u4f4d\u65bd\u52a0\u3010\u5bd2\u51b7\u3011\u7684\u8303\u56f4\u6027\u5bd2\u6d41",
            "hardStagedId": "act13mini_07#f#",
            "dangerLevel": "\u7cbe\u82f12 LV.15",
            "dangerPoint": -1.0,
            "loadingPicId": "loading_LM_frost",
            "canPractice": true,
            "canBattleReplay": true,
            "apCost": 21,
            "apFailReturn": 20,
            "etItemId": null,
            "etCost": -1,
            "etFailReturn": -1,
            "etButtonStyle": null,
            "apProtectTimes": 1,
            "diamondOnceDrop": 1,
            "practiceTicketCost": 1,
            "dailyStageDifficulty": 0,
            "expGain": 210,
            "goldGain": 210,
            "loseExpGain": 0,
            "loseGoldGain": 0,
            "passFavor": 20,
            "completeFavor": 21,
            "slProgress": 0,
            "displayMainItem": null,
            "hilightMark": false,
            "bossMark": false,
            "isPredefined": false,
            "isHardPredefined": false,
            "isSkillSelectablePredefined": false,
            "isStoryOnly": false,
            "appearanceStyle": "MAIN_NORMAL",
            "stageDropInfo": {
                "firstPassRewards": null,
                "firstCompleteRewards": null,
                "passRewards": null,
                "completeRewards": null,
                "displayRewards": [
                    {
                        "type": "ACTIVITY_ITEM",
                        "id": "act13mini_token_can",
                        "dropType": "COMPLETE"
                    },
                    {
                        "type": "ACTIVITY_ITEM",
                        "id": "act13mini_token_can",
                        "dropType": "SPECIAL"
                    },
                    {
                        "type": "MATERIAL",
                        "id": "30033",
                        "dropType": "NORMAL"
                    },
                    {
                        "type": "DIAMOND",
                        "id": "4002",
                        "dropType": "COMPLETE"
                    }
                ],
                "displayDetailRewards": [
                    {
                        "occPercent": "ALWAYS",
                        "type": "ACTIVITY_ITEM",
                        "id": "act13mini_token_can",
                        "dropType": "COMPLETE"
                    },
                    {
                        "occPercent": "ALWAYS",
                        "type": "ACTIVITY_ITEM",
                        "id": "act13mini_token_can",
                        "dropType": "SPECIAL"
                    },
                    {
                        "occPercent": "USUAL",
                        "type": "MATERIAL",
                        "id": "30033",
                        "dropType": "NORMAL"
                    },
                    {
                        "occPercent": "SOMETIMES",
                        "type": "MATERIAL",
                        "id": "30021",
                        "dropType": "ADDITIONAL"
                    },
                    {
                        "occPercent": "SOMETIMES",
                        "type": "MATERIAL",
                        "id": "30041",
                        "dropType": "ADDITIONAL"
                    },
                    {
                        "occPercent": "SOMETIMES",
                        "type": "CARD_EXP",
                        "id": "2001",
                        "dropType": "ADDITIONAL"
                    },
                    {
                        "occPercent": "OFTEN",
                        "type": "MATERIAL",
                        "id": "30022",
                        "dropType": "ADDITIONAL"
                    },
                    {
                        "occPercent": "SOMETIMES",
                        "type": "MATERIAL",
                        "id": "30042",
                        "dropType": "ADDITIONAL"
                    },
                    {
                        "occPercent": "SOMETIMES",
                        "type": "CARD_EXP",
                        "id": "2002",
                        "dropType": "ADDITIONAL"
                    },
                    {
                        "occPercent": "SOMETIMES",
                        "type": "MATERIAL",
                        "id": "30023",
                        "dropType": "ADDITIONAL"
                    },
                    {
                        "occPercent": "SOMETIMES",
                        "type": "MATERIAL",
                        "id": "30043",
                        "dropType": "ADDITIONAL"
                    },
                    {
                        "occPercent": "SOMETIMES",
                        "type": "MATERIAL",
                        "id": "30083",
                        "dropType": "ADDITIONAL"
                    },
                    {
                        "occPercent": "SOMETIMES",
                        "type": "MATERIAL",
                        "id": "31023",
                        "dropType": "ADDITIONAL"
                    },
                    {
                        "occPercent": "SOMETIMES",
                        "type": "CARD_EXP",
                        "id": "2003",
                        "dropType": "ADDITIONAL"
                    },
                    {
                        "occPercent": "ALWAYS",
                        "type": "DIAMOND",
                        "id": "4002",
                        "dropType": "COMPLETE"
                    }
                ]
            },
            "canUseCharm": false,
            "canUseTech": false,
            "canUseTrapTool": false,
            "canUseBattlePerformance": false,
            "startButtonOverrideId": null,
            "isStagePatch": false,
            "mainStageId": "act13mini_01",
            "extraCondition": null,
            "extraInfo": null
        },
        {
            "stageType": "ACTIVITY",
            "difficulty": "FOUR_STAR",
            "performanceStageFlag": "NORMAL_STAGE",
            "diffGroup": "NONE",
            "unlockCondition": [
                {
                    "stageId": "main_02-08",
                    "completeState": "PASS"
                },
                {
                    "stageId": "act13mini_07",
                    "completeState": "COMPLETE"
                }
            ],
            "stageId": "act13mini_07#f#",
            "levelId": "Activities/act13mini/level_act13mini_07",
            "zoneId": "act13mini_zone1",
            "code": "BW-7",
            "name": "\u96ea\u5929\u8def\u6ed1",
            "description": "<@lv.fs>\u9644\u52a0\u6761\u4ef6\uff1a</>\\n\u51b0\u7206\u6e90\u77f3\u866b\u7684\u7279\u6b8a\u80fd\u529b\u4e0d\u4f1a\u5931\u6548",
            "hardStagedId": null,
            "dangerLevel": "-",
            "dangerPoint": -1.0,
            "loadingPicId": "loading_LM_frost",
            "canPractice": true,
            "canBattleReplay": false,
            "apCost": 21,
            "apFailReturn": 10,
            "etItemId": null,
            "etCost": -1,
            "etFailReturn": -1,
            "etButtonStyle": null,
            "apProtectTimes": 0,
            "diamondOnceDrop": 1,
            "practiceTicketCost": 3,
            "dailyStageDifficulty": 0,
            "expGain": 210,
            "goldGain": 210,
            "loseExpGain": 0,
            "loseGoldGain": 0,
            "passFavor": 10,
            "completeFavor": 21,
            "slProgress": 0,
            "displayMainItem": null,
            "hilightMark": false,
            "bossMark": false,
            "isPredefined": false,
            "isHardPredefined": false,
            "isSkillSelectablePredefined": false,
            "isStoryOnly": false,
            "appearanceStyle": "MAIN_NORMAL",
            "stageDropInfo": {
                "firstPassRewards": null,
                "firstCompleteRewards": null,
                "passRewards": null,
                "completeRewards": null,
                "displayRewards": [
                    {
                        "type": "ACTIVITY_ITEM",
                        "id": "act13mini_token_can",
                        "dropType": "ONCE"
                    },
                    {
                        "type": "DIAMOND",
                        "id": "4002",
                        "dropType": "COMPLETE"
                    }
                ],
                "displayDetailRewards": [
                    {
                        "occPercent": "ALWAYS",
                        "type": "ACTIVITY_ITEM",
                        "id": "act13mini_token_can",
                        "dropType": "ONCE"
                    },
                    {
                        "occPercent": "ALWAYS",
                        "type": "DIAMOND",
                        "id": "4002",
                        "dropType": "COMPLETE"
                    }
                ]
            },
            "canUseCharm": false,
            "canUseTech": false,
            "canUseTrapTool": false,
            "canUseBattlePerformance": false,
            "startButtonOverrideId": null,
            "isStagePatch": false,
            "mainStageId": "act13mini_01",
            "extraCondition": null,
            "extraInfo": null
        },
        {
            "stageType": "ACTIVITY",
            "difficulty": "NORMAL",
            "performanceStageFlag": "NORMAL_STAGE",
            "diffGroup": "NONE",
            "unlockCondition": [
                {
                    "stageId": "act13mini_07",
                    "completeState": "PASS"
                }
            ],
            "stageId": "act13mini_08",
            "levelId": "Activities/act13mini/level_act13mini_08",
            "zoneId": "act13mini_zone1",
            "code": "BW-8",
            "name": "\u51cc\u7a7a\u800c\u8fc7",
            "description": "\u7b3c\u7f69\u6218\u573a\u7684\u5929\u5e55\u4e0d\u4f1a\u6709\u6210\u7fa4\u7ed3\u961f\u7684\u7fbd\u517d\u63a0\u8fc7\uff0c\u51db\u7136\u800c\u81f3\u7684\u53ea\u6709\u6d53\u6d53\u6740\u673a\u3002\\n<@lv.item><\u9632\u7a7a\u7b26\u6587></>\u7f6e\u4e8e\u5176\u4e2d\u7684\u5e72\u5458\u4f1a\u7565\u5fae\u51cf\u6162\u653b\u901f\uff0c\u4f46\u5927\u5e45\u5ea6\u63d0\u5347\u5bf9\u7a7a\u653b\u51fb\u529b\\n<@lv.item><\u5f29\u70ae\u53f0></>\u4f1a\u5b9a\u671f\u5c04\u51fa\u5f29\u7bad\u5bf9\u6211\u65b9\u5355\u4f4d\u9020\u6210\u7269\u7406\u4f24\u5bb3",
            "hardStagedId": "act13mini_08#f#",
            "dangerLevel": "\u7cbe\u82f12 LV.25",
            "dangerPoint": -1.0,
            "loadingPicId": "loading2",
            "canPractice": true,
            "canBattleReplay": true,
            "apCost": 21,
            "apFailReturn": 20,
            "etItemId": null,
            "etCost": -1,
            "etFailReturn": -1,
            "etButtonStyle": null,
            "apProtectTimes": 1,
            "diamondOnceDrop": 1,
            "practiceTicketCost": 1,
            "dailyStageDifficulty": 0,
            "expGain": 210,
            "goldGain": 210,
            "loseExpGain": 0,
            "loseGoldGain": 0,
            "passFavor": 20,
            "completeFavor": 21,
            "slProgress": 0,
            "displayMainItem": null,
            "hilightMark": false,
            "bossMark": false,
            "isPredefined": false,
            "isHardPredefined": false,
            "isSkillSelectablePredefined": false,
            "isStoryOnly": false,
            "appearanceStyle": "MAIN_NORMAL",
            "stageDropInfo": {
                "firstPassRewards": null,
                "firstCompleteRewards": null,
                "passRewards": null,
                "completeRewards": null,
                "displayRewards": [
                    {
                        "type": "ACTIVITY_ITEM",
                        "id": "act13mini_token_can",
                        "dropType": "COMPLETE"
                    },
                    {
                        "type": "ACTIVITY_ITEM",
                        "id": "act13mini_token_can",
                        "dropType": "SPECIAL"
                    },
                    {
                        "type": "MATERIAL",
                        "id": "30093",
                        "dropType": "NORMAL"
                    },
                    {
                        "type": "DIAMOND",
                        "id": "4002",
                        "dropType": "COMPLETE"
                    }
                ],
                "displayDetailRewards": [
                    {
                        "occPercent": "ALWAYS",
                        "type": "ACTIVITY_ITEM",
                        "id": "act13mini_token_can",
                        "dropType": "COMPLETE"
                    },
                    {
                        "occPercent": "ALWAYS",
                        "type": "ACTIVITY_ITEM",
                        "id": "act13mini_token_can",
                        "dropType": "SPECIAL"
                    },
                    {
                        "occPercent": "OFTEN",
                        "type": "MATERIAL",
                        "id": "30093",
                        "dropType": "NORMAL"
                    },
                    {
                        "occPercent": "OFTEN",
                        "type": "MATERIAL",
                        "id": "30031",
                        "dropType": "ADDITIONAL"
                    },
                    {
                        "occPercent": "OFTEN",
                        "type": "MATERIAL",
                        "id": "30051",
                        "dropType": "ADDITIONAL"
                    },
                    {
                        "occPercent": "SOMETIMES",
                        "type": "MATERIAL",
                        "id": "30032",
                        "dropType": "ADDITIONAL"
                    },
                    {
                        "occPercent": "SOMETIMES",
                        "type": "MATERIAL",
                        "id": "30052",
                        "dropType": "ADDITIONAL"
                    },
                    {
                        "occPercent": "SOMETIMES",
                        "type": "MATERIAL",
                        "id": "30033",
                        "dropType": "ADDITIONAL"
                    },
                    {
                        "occPercent": "SOMETIMES",
                        "type": "MATERIAL",
                        "id": "30053",
                        "dropType": "ADDITIONAL"
                    },
                    {
                        "occPercent": "SOMETIMES",
                        "type": "MATERIAL",
                        "id": "30093",
                        "dropType": "ADDITIONAL"
                    },
                    {
                        "occPercent": "SOMETIMES",
                        "type": "MATERIAL",
                        "id": "31033",
                        "dropType": "ADDITIONAL"
                    },
                    {
                        "occPercent": "SOMETIMES",
                        "type": "MATERIAL",
                        "id": "30103",
                        "dropType": "ADDITIONAL"
                    },
                    {
                        "occPercent": "SOMETIMES",
                        "type": "MATERIAL",
                        "id": "31053",
                        "dropType": "ADDITIONAL"
                    },
                    {
                        "occPercent": "SOMETIMES",
                        "type": "MATERIAL",
                        "id": "31043",
                        "dropType": "ADDITIONAL"
                    },
                    {
                        "occPercent": "ALWAYS",
                        "type": "DIAMOND",
                        "id": "4002",
                        "dropType": "COMPLETE"
                    }
                ]
            },
            "canUseCharm": false,
            "canUseTech": false,
            "canUseTrapTool": false,
            "canUseBattlePerformance": false,
            "startButtonOverrideId": null,
            "isStagePatch": false,
            "mainStageId": "act13mini_01",
            "extraCondition": null,
            "extraInfo": null
        },
        {
            "stageType": "ACTIVITY",
            "difficulty": "FOUR_STAR",
            "performanceStageFlag": "NORMAL_STAGE",
            "diffGroup": "NONE",
            "unlockCondition": [
                {
                    "stageId": "main_02-08",
                    "completeState": "PASS"
                },
                {
                    "stageId": "act13mini_08",
                    "completeState": "COMPLETE"
                }
            ],
            "stageId": "act13mini_08#f#",
            "levelId": "Activities/act13mini/level_act13mini_08",
            "zoneId": "act13mini_zone1",
            "code": "BW-8",
            "name": "\u51cc\u7a7a\u800c\u8fc7",
            "description": "<@lv.fs>\u9644\u52a0\u6761\u4ef6\uff1a</>\\n<@lv.item><\u5f29\u70ae\u53f0></>\u9020\u6210\u7684\u4f24\u5bb3\u63d0\u9ad8",
            "hardStagedId": null,
            "dangerLevel": "-",
            "dangerPoint": -1.0,
            "loadingPicId": "loading2",
            "canPractice": true,
            "canBattleReplay": false,
            "apCost": 21,
            "apFailReturn": 10,
            "etItemId": null,
            "etCost": -1,
            "etFailReturn": -1,
            "etButtonStyle": null,
            "apProtectTimes": 0,
            "diamondOnceDrop": 1,
            "practiceTicketCost": 3,
            "dailyStageDifficulty": 0,
            "expGain": 210,
            "goldGain": 210,
            "loseExpGain": 0,
            "loseGoldGain": 0,
            "passFavor": 10,
            "completeFavor": 21,
            "slProgress": 0,
            "displayMainItem": null,
            "hilightMark": false,
            "bossMark": false,
            "isPredefined": false,
            "isHardPredefined": false,
            "isSkillSelectablePredefined": false,
            "isStoryOnly": false,
            "appearanceStyle": "MAIN_NORMAL",
            "stageDropInfo": {
                "firstPassRewards": null,
                "firstCompleteRewards": null,
                "passRewards": null,
                "completeRewards": null,
                "displayRewards": [
                    {
                        "type": "FURN",
                        "id": "furni_dropS026_gluttony_01",
                        "dropType": "ONCE"
                    },
                    {
                        "type": "ACTIVITY_ITEM",
                        "id": "act13mini_token_can",
                        "dropType": "ONCE"
                    },
                    {
                        "type": "DIAMOND",
                        "id": "4002",
                        "dropType": "COMPLETE"
                    }
                ],
                "displayDetailRewards": [
                    {
                        "occPercent": "ALWAYS",
                        "type": "FURN",
                        "id": "furni_dropS026_gluttony_01",
                        "dropType": "ONCE"
                    },
                    {
                        "occPercent": "ALWAYS",
                        "type": "ACTIVITY_ITEM",
                        "id": "act13mini_token_can",
                        "dropType": "ONCE"
                    },
                    {
                        "occPercent": "ALWAYS",
                        "type": "DIAMOND",
                        "id": "4002",
                        "dropType": "COMPLETE"
                    }
                ]
            },
            "canUseCharm": false,
            "canUseTech": false,
            "canUseTrapTool": false,
            "canUseBattlePerformance": false,
            "startButtonOverrideId": null,
            "isStagePatch": false,
            "mainStageId": "act13mini_01",
            "extraCondition": null,
            "extraInfo": null
        },
        {
            "stageType": "ACTIVITY",
            "difficulty": "NORMAL",
            "performanceStageFlag": "NORMAL_STAGE",
            "diffGroup": "NONE",
            "unlockCondition": [
                {
                    "stageId": "act13mini_03",
                    "completeState": "PASS"
                }
            ],
            "stageId": "act13mini_s01",
            "levelId": "Activities/act13mini/level_act13mini_sub-1-1",
            "zoneId": "act13mini_zone1",
            "code": "BW-S-1",
            "name": "\u4fdd\u536b\u963f\u6839",
            "description": "\u963f\u6839\uff0c\u770b\u8d77\u6765\u8fd9\u4e9b\u5c0f\u52a8\u7269\u597d\u50cf\u90fd\u662f\u51b2\u4f60\u6765\u7684\u554a\u3002\u54ce\uff1f\uff01\u963f\u6839\u4f60\u53bb\u54ea\u91cc\u4e86\uff1f\\n<@lv.item><\u56fa\u5b9a\u7f16\u961f></>\u4f7f\u7528\u56fa\u5b9a\u5e72\u5458\u8fdb\u884c\u4f5c\u6218",
            "hardStagedId": null,
            "dangerLevel": "-",
            "dangerPoint": -1.0,
            "loadingPicId": "loading_PL_Downtown",
            "canPractice": false,
            "canBattleReplay": false,
            "apCost": 0,
            "apFailReturn": 0,
            "etItemId": null,
            "etCost": -1,
            "etFailReturn": -1,
            "etButtonStyle": null,
            "apProtectTimes": 0,
            "diamondOnceDrop": 1,
            "practiceTicketCost": -1,
            "dailyStageDifficulty": 0,
            "expGain": 0,
            "goldGain": 0,
            "loseExpGain": 0,
            "loseGoldGain": 0,
            "passFavor": 0,
            "completeFavor": 0,
            "slProgress": 0,
            "displayMainItem": null,
            "hilightMark": false,
            "bossMark": false,
            "isPredefined": true,
            "isHardPredefined": false,
            "isSkillSelectablePredefined": false,
            "isStoryOnly": false,
            "appearanceStyle": "MAIN_NORMAL",
            "stageDropInfo": {
                "firstPassRewards": null,
                "firstCompleteRewards": null,
                "passRewards": null,
                "completeRewards": null,
                "displayRewards": [
                    {
                        "type": "DIAMOND",
                        "id": "4002",
                        "dropType": "COMPLETE"
                    }
                ],
                "displayDetailRewards": [
                    {
                        "occPercent": "ALWAYS",
                        "type": "DIAMOND",
                        "id": "4002",
                        "dropType": "COMPLETE"
                    }
                ]
            },
            "canUseCharm": false,
            "canUseTech": false,
            "canUseTrapTool": false,
            "canUseBattlePerformance": false,
            "startButtonOverrideId": null,
            "isStagePatch": false,
            "mainStageId": "act13mini_01",
            "extraCondition": null,
            "extraInfo": null
        }
    ]
}